libcasm/include/casm/mapping/AtomMapping.hh
libcasm/include/casm/mapping/LatticeMapping.hh
libcasm/include/casm/mapping/MappingSearch.hh
libcasm/include/casm/mapping/SearchData.hh
libcasm/include/casm/mapping/StructureMapping.hh
libcasm/include/casm/mapping/atom_cost.hh
libcasm/include/casm/mapping/hungarian.hh
libcasm/include/casm/mapping/lattice_cost.hh
libcasm/include/casm/mapping/map_atoms.hh
libcasm/include/casm/mapping/map_lattices.hh
libcasm/include/casm/mapping/map_structures.hh
libcasm/include/casm/mapping/misc.hh
libcasm/include/casm/mapping/murty.hh
libcasm/include/casm/mapping/version.hh
libcasm/include/casm/mapping/impl/LatticeMap.hh
libcasm/include/casm/mapping/impl/SimpleStrucMapCalculator.hh
libcasm/include/casm/mapping/impl/StrucMapCalculatorInterface.hh
libcasm/include/casm/mapping/impl/StrucMapping.hh
libcasm/include/casm/mapping/impl/io/json/StrucMapping_json_io.hh
libcasm/include/casm/mapping/io/json_io.hh
libcasm/lib/libcasm_mapping.so
libcasm/mapping/__init__.py
libcasm/mapping/info/__init__.py
libcasm/mapping/info/_mapping_info.cpython-311-x86_64-linux-gnu.so
libcasm/mapping/mapsearch/__init__.py
libcasm/mapping/mapsearch/_mapping_mapsearch.cpython-311-x86_64-linux-gnu.so
libcasm/mapping/methods/__init__.py
libcasm/mapping/methods/_mapping_methods.cpython-311-x86_64-linux-gnu.so
libcasm/mapping/methods/_methods.py
libcasm/share/CASMcode_mapping/cmake/CASMcode_mappingConfig.cmake
libcasm/share/CASMcode_mapping/cmake/CASMcode_mappingConfigVersion.cmake
libcasm/share/CASMcode_mapping/cmake/CASMcode_mappingTargets-release.cmake
libcasm/share/CASMcode_mapping/cmake/CASMcode_mappingTargets.cmake
libcasm_mapping-2.4.0.dist-info/licenses/LICENSE
libcasm_mapping-2.4.0.dist-info/METADATA
libcasm_mapping-2.4.0.dist-info/WHEEL
libcasm_mapping-2.4.0.dist-info/top_level.txt
libcasm_mapping-2.4.0.dist-info/RECORD
